MANIFEST.in
README.rst
buildout.cfg
develop.cfg
requirements.txt
setup.py
version.txt
bob/__init__.py
bob.db.asvspoof.egg-info/PKG-INFO
bob.db.asvspoof.egg-info/SOURCES.txt
bob.db.asvspoof.egg-info/dependency_links.txt
bob.db.asvspoof.egg-info/entry_points.txt
bob.db.asvspoof.egg-info/not-zip-safe
bob.db.asvspoof.egg-info/requires.txt
bob.db.asvspoof.egg-info/top_level.txt
bob/db/__init__.py
bob/db/asvspoof/__init__.py
bob/db/asvspoof/checkfiles.py
bob/db/asvspoof/create.py
bob/db/asvspoof/driver.py
bob/db/asvspoof/dumplist.py
bob/db/asvspoof/models.py
bob/db/asvspoof/query.py
bob/db/asvspoof/test.py
bob/db/asvspoof/protocols/ASV_female_development.ndx
bob/db/asvspoof/protocols/ASV_female_enrolment.ndx
bob/db/asvspoof/protocols/ASV_female_evaluation.ndx
bob/db/asvspoof/protocols/ASV_male_development.ndx
bob/db/asvspoof/protocols/ASV_male_enrolment.ndx
bob/db/asvspoof/protocols/ASV_male_evaluation.ndx
bob/db/asvspoof/protocols/as_develop.ndx
bob/db/asvspoof/protocols/as_evaluation.ndx
bob/db/asvspoof/protocols/as_train.trn
bob/db/asvspoof/protocols/cm_develop.ndx
bob/db/asvspoof/protocols/cm_evaluation.ndx
bob/db/asvspoof/protocols/cm_train.trn
doc/conf.py
doc/index.rst